vedastro/__init__.py
vedastro/build.sh
vedastro/calculate.py
vedastro/meta.yaml
vedastro/runtimeconfig.json
vedastro/update_check.py
vedastro/vedastro.py
vedastro-1.23.18.dist-info/LICENSE
vedastro-1.23.18.dist-info/METADATA
vedastro-1.23.18.dist-info/WHEEL
vedastro-1.23.18.dist-info/RECORD
