Metadata-Version: 2.3
Name: VedAstro
Version: 1.23.18
Summary: An open source Python library for advanced astronomical calculations like planet longitude, house sign, shadbala, etc...
Author: Tharaka Umayanga
Author-email: tharakau@gmail.com
Requires-Python: >=3.9,<3.13
Classifier: Programming Language :: Python :: 3
Classifier: Programming Language :: Python :: 3.9
Classifier: Programming Language :: Python :: 3.10
Classifier: Programming Language :: Python :: 3.11
Classifier: Programming Language :: Python :: 3.12
Requires-Dist: colorama
Requires-Dist: packaging
Requires-Dist: pycparser
Requires-Dist: pythonnet (>=3.0.1,<4.0.0)
Requires-Dist: requests
